{
  "allTours": [
    {
      "tourId": 1,
      "name": "Pérez Art Museum Miami",
      "city": "Miami",
      "description": "The Pérez Art Museum Miami —officially known as the Jorge M. Pérez Art Museum of Miami......",
      "price": "$50 - $100",
      "priceStart": 50,
      "priceEnd": 100,
      "duration": "1 day",
      "endDate": "",
      "startDate": "1681813148146",
      "facilities": [],
      "bookedBy": 2,
      "mainImg": "assets/tours/tour-1.png"
    },
    {
      "tourId": 2,
      "name": "Hard Rock Stadium",
      "city": "Miami",
      "description": "Hard Rock Stadium is a multi-purpose stadium located in Miami Gardens, Florida, a city......",
      "price": "$100 - $150",
      "priceStart": 100,
      "priceEnd": 150,
      "duration": "1 day",
      "endDate": "",
      "startDate": "",
      "facilities": [],
      "bookedBy": 3,
      "mainImg": "assets/tours/tour-2.png"
    },
    {
      "tourId": 3,
      "name": "Matheson Hammock Park",
      "city": "Islamabad",
      "description": "Matheson Hammock Park is a 630 acres urban park in metropolitan Miami at 9610 Old .....",
      "price": "$150 - $250",
      "priceStart": 150,
      "priceEnd": 250,
      "duration": "1 day",
      "endDate": "",
      "startDate": "",
      "facilities": [],
      "bookedBy": 2,
      "mainImg": "assets/tours/tour-3.png"
    },
    {
      "tourId": 4,
      "name": "The Wharf Miami",
      "city": "London",
      "description": "An all new outdoor pop-up event space  anchored with live music, eats, cocktails.........",
      "price": "$250 - $300",
      "priceStart": 250,
      "priceEnd": 300,
      "duration": "1 day",
      "endDate": "",
      "startDate": "",
      "facilities": [],
      "bookedBy": 3,
      "mainImg": "assets/tours/tour-4.png"
    },
    {
      "tourId": 5,
      "name": "Miami Tower",
      "city": "Dubai",
      "description": "Views of Biscayne Bay & the downtown Miam i skyline from climate-controlled glass gondolas.",
      "price": "$300 - $350",
      "priceStart": 300,
      "priceEnd": 350,
      "duration": "1 day",
      "endDate": "",
      "startDate": "",
      "facilities": [],
      "bookedBy": 4,
      "mainImg": "assets/tours/tour-5.png"
    },
    {
      "tourId": 6,
      "name": "Skyviews Miami",
      "city": "Miami",
      "description": "Views of Biscayne Bay & the downtown Miam i skyline from climate-controlled glass gondolas.",
      "price": "$250 - $500",
      "priceStart": 250,
      "priceEnd": 500,
      "duration": "1 day",
      "endDate": "",
      "startDate": "",
      "facilities": [],
      "bookedBy": 3,
      "mainImg": "assets/tours/tour-6.png"
    }
  ],
  "myTours": [
    {
      "tourId": 1,
      "name": "Pérez Art Museum Miami",
      "city": "Miami",
      "description": "Matheson Hammock Park is a 630 acres urban park in metropolitan Miami at 9610 Old .....",
      "price": "$50 - $100",
      "priceStart": 50,
      "priceEnd": 100,
      "duration": "1 day",
      "endDate": "",
      "startDate": "",
      "facilities": [],
      "bookedBy": 2,
      "mainImg": "assets/tours/tour-1.png"
    },
    {
      "tourId": 3,
      "name": "Matheson Hammock Park",
      "city": "Islamabad",
      "description": "Matheson Hammock Park is a 630 acres urban park in metropolitan Miami at 9610 Old .....",
      "price": "$150 - $250",
      "priceStart": 150,
      "priceEnd": 250,
      "duration": "1 day",
      "endDate": "",
      "startDate": "",
      "facilities": [],
      "bookedBy": 2,
      "mainImg": "assets/tours/tour-3.png"
    }
  ]
}
